hummingbot/VERSION
hummingbot/__init__.py
hummingbot/exceptions.py
hummingbot/client/__init__.py
hummingbot/client/hummingbot_application.py
hummingbot/client/performance.py
hummingbot/client/platform.py
hummingbot/client/settings.py
hummingbot/client/command/__init__.py
hummingbot/client/command/balance_command.py
hummingbot/client/command/command_utils.py
hummingbot/client/command/config_command.py
hummingbot/client/command/connect_command.py
hummingbot/client/command/create_command.py
hummingbot/client/command/exit_command.py
hummingbot/client/command/export_command.py
hummingbot/client/command/gateway_api_manager.py
hummingbot/client/command/gateway_approve_command.py
hummingbot/client/command/gateway_command.py
hummingbot/client/command/gateway_config_command.py
hummingbot/client/command/gateway_lp_command.py
hummingbot/client/command/gateway_pool_command.py
hummingbot/client/command/gateway_swap_command.py
hummingbot/client/command/gateway_token_command.py
hummingbot/client/command/help_command.py
hummingbot/client/command/history_command.py
hummingbot/client/command/import_command.py
hummingbot/client/command/lp_command_utils.py
hummingbot/client/command/mqtt_command.py
hummingbot/client/command/order_book_command.py
hummingbot/client/command/rate_command.py
hummingbot/client/command/silly_commands.py
hummingbot/client/command/start_command.py
hummingbot/client/command/status_command.py
hummingbot/client/command/stop_command.py
hummingbot/client/command/ticker_command.py
hummingbot/client/config/__init__.py
hummingbot/client/config/client_config_map.py
hummingbot/client/config/conf_migration.py
hummingbot/client/config/config_crypt.py
hummingbot/client/config/config_data_types.py
hummingbot/client/config/config_helpers.py
hummingbot/client/config/config_methods.py
hummingbot/client/config/config_validators.py
hummingbot/client/config/config_var.py
hummingbot/client/config/fee_overrides_config_map.py
hummingbot_quang-20251017.dist-info/METADATA
hummingbot_quang-20251017.dist-info/WHEEL
hummingbot_quang-20251017.dist-info/top_level.txt
hummingbot_quang-20251017.dist-info/RECORD
hummingbot_quang-20251017.dist-info/licenses/LICENSE
